acoriss_payment_gateway/__init__.py
acoriss_payment_gateway/client.py
acoriss_payment_gateway/errors.py
acoriss_payment_gateway/py.typed
acoriss_payment_gateway/signer.py
acoriss_payment_gateway/types.py
acoriss_payment_gateway-0.1.3.dist-info/licenses/LICENSE
acoriss_payment_gateway-0.1.3.dist-info/METADATA
acoriss_payment_gateway-0.1.3.dist-info/WHEEL
acoriss_payment_gateway-0.1.3.dist-info/top_level.txt
acoriss_payment_gateway-0.1.3.dist-info/RECORD
