Metadata-Version: 2.4
Name: acoriss-payment-gateway
Version: 0.1.3
Summary: Python SDK for Acoriss Payment Gateway
Author-email: Acoriss <info@acoriss.com>
License: MIT
Project-URL: Homepage, https://github.com/Acoriss-RDC/payment-gateway-python-sdk
Project-URL: Repository, https://github.com/Acoriss-RDC/payment-gateway-python-sdk
Project-URL: Documentation, https://github.com/Acoriss-RDC/payment-gateway-python-sdk#readme
Keywords: payments,sdk,checkout,acoriss
Classifier: Development Status :: 4 - Beta
Classifier: Intended Audience :: Developers
Classifier: License :: OSI Approved :: MIT License
Classifier: Programming Language :: Python :: 3
Classifier: Programming Language :: Python :: 3.8
Classifier: Programming Language :: Python :: 3.9
Classifier: Programming Language :: Python :: 3.10
Classifier: Programming Language :: Python :: 3.11
Classifier: Programming Language :: Python :: 3.12
Classifier: Topic :: Software Development :: Libraries :: Python Modules
Requires-Python: >=3.8
License-File: LICENSE
Requires-Dist: requests>=2.31.0
Provides-Extra: dev
Requires-Dist: pytest>=7.4.0; extra == "dev"
Requires-Dist: pytest-cov>=4.1.0; extra == "dev"
Requires-Dist: pytest-mock>=3.11.0; extra == "dev"
Requires-Dist: mypy>=1.5.0; extra == "dev"
Requires-Dist: ruff>=0.0.292; extra == "dev"
Requires-Dist: types-requests>=2.31.0; extra == "dev"
Dynamic: license-file
